README.md
setup.cfg
setup.py
versioneer.py
BiginPythonClient/BiginClient.py
BiginPythonClient/BiginLoginSession.py
BiginPythonClient/BiginModules.py
BiginPythonClient/__init__.py
BiginPythonClient.egg-info/PKG-INFO
BiginPythonClient.egg-info/SOURCES.txt
BiginPythonClient.egg-info/dependency_links.txt
BiginPythonClient.egg-info/not-zip-safe
BiginPythonClient.egg-info/requires.txt
BiginPythonClient.egg-info/top_level.txt