Metadata-Version: 2.4
Name: BiginPythonClient
Version: 0.0.8
Summary: Python package which provides Bigin Rest API Client
Home-page: https://github.com/rmetcalf9/BiginPythonClient
Author: Robert Metcalf
Author-email: rmetcalf9@googlemail.com
License: MIT
Requires-Dist: requests==2.31.0
Requires-Dist: pytz==2019.3
Requires-Dist: python-dateutil==2.8.1
Requires-Dist: PythonAPIClientBase==0.0.15
Requires-Dist: InquirerPy==0.3.4
Dynamic: author
Dynamic: author-email
Dynamic: description
Dynamic: description-content-type
Dynamic: home-page
Dynamic: license
Dynamic: requires-dist
Dynamic: summary
